randomorgpy/Client.py
randomorgpy/Exceptions.py
randomorgpy/__init__.py
randomorgpy-0.2.dist-info/METADATA
randomorgpy-0.2.dist-info/WHEEL
randomorgpy-0.2.dist-info/licenses/LICENSE
randomorgpy-0.2.dist-info/RECORD
