Metadata-Version: 2.3
Name: randomorgpy
Version: 0.2
Summary: A small python wrapper for the random.org Basic API
Project-URL: documentation, https://fhune.de/randomorgpy_documentation
Project-URL: github, https://github.com/playlix42/randomorgpy
Author-email: DouglasAdams_42 <felix.hune@gmx.de>
License-File: LICENSE
Classifier: License :: OSI Approved :: GNU Lesser General Public License v3 (LGPLv3)
Classifier: Operating System :: OS Independent
Classifier: Programming Language :: Python :: 3
Requires-Python: >=3.7
